jupdf/__init__.py
jupdf/pypdfnb.py
jupdf/pypdfnb_converter.py
jupdf/pypdfnb_jobs.py
jupdf/pypdfnb_parsing.py
jupdf/tex/modded_eisvogel.tex
jupdf-0.1.2.dist-info/METADATA
jupdf-0.1.2.dist-info/WHEEL
jupdf-0.1.2.dist-info/top_level.txt
jupdf-0.1.2.dist-info/RECORD
