Metadata-Version: 2.1
Name: jupdf
Version: 0.1.2
Summary: A small Python package to convert Jupyter Notebook files to single PDF files via the use of Pandoc.
Home-page: https://github.com/Catterall/jupdf
Download-URL: https://github.com/Catterall/jupdf/releases
Author: KCatterall
License: MIT
Requires-Dist: PyMuPDF>=1.24.10
Requires-Dist: PyMuPDFb>=1.24.10
Requires-Dist: pandocfilters>=1.5.1
